CHANGES.txt
DEPENDENCES.txt
README.txt
setup.py
src/ng/__init__.py
src/ng.site.addon.community.egg-info/PKG-INFO
src/ng.site.addon.community.egg-info/SOURCES.txt
src/ng.site.addon.community.egg-info/dependency_links.txt
src/ng.site.addon.community.egg-info/namespace_packages.txt
src/ng.site.addon.community.egg-info/not-zip-safe
src/ng.site.addon.community.egg-info/requires.txt
src/ng.site.addon.community.egg-info/top_level.txt
src/ng/site/__init__.py
src/ng/site/addon/__init__.py
src/ng/site/addon/community/__init__.py
src/ng/site/addon/community/configure.zcml
src/ng/site/addon/community/ng.site.addon.community.txt
src/ng/site/addon/community/communityfactory/__init__.py
src/ng/site/addon/community/communityfactory/community.py
src/ng/site/addon/community/communityfactory/configure.zcml
src/ng/site/addon/community/communityfactory/interfaces.py
src/ng/site/addon/community/contain/__init__.py
src/ng/site/addon/community/contain/configure.zcml
src/ng/site/addon/community/contain/interfaces.py
src/ng/site/addon/community/etc/ng.site.addon.community-configure.zcml
src/ng/site/addon/community/install/__init__.py
src/ng/site/addon/community/install/configure.zcml
src/ng/site/addon/community/install/install_content.py
src/ng/site/addon/community/profile/__init__.py
src/ng/site/addon/community/profile/configure.zcml
src/ng/site/addon/community/profile/create_profile_handle.py